pyharmonics/__init__.py
pyharmonics/constants.py
pyharmonics/patterns.py
pyharmonics/positions.py
pyharmonics/quick.py
pyharmonics/technicals.py
pyharmonics/utils.py
pyharmonics/marketdata/__init__.py
pyharmonics/marketdata/alpaca.py
pyharmonics/marketdata/binance_data.py
pyharmonics/marketdata/candle_base.py
pyharmonics/marketdata/yahoo.py
pyharmonics/plotter/__init__.py
pyharmonics/plotter/harmonic.py
pyharmonics/plotter/option.py
pyharmonics/search/__init__.py
pyharmonics/search/divergence.py
pyharmonics/search/harmonic.py
pyharmonics-1.5.3.dist-info/LICENSE
pyharmonics-1.5.3.dist-info/METADATA
pyharmonics-1.5.3.dist-info/WHEEL
pyharmonics-1.5.3.dist-info/top_level.txt
pyharmonics-1.5.3.dist-info/RECORD
