Metadata-Version: 2.2
Name: pyharmonics
Version: 1.5.3
Author-email: Niall O'Connor <zechs.marquie@gmail.com>
Classifier: Programming Language :: Python :: 3
Classifier: License :: OSI Approved :: MIT License
Classifier: Operating System :: OS Independent
Requires-Python: >=3.7
License-File: LICENSE
Requires-Dist: yfinance
Requires-Dist: alpaca-trade-api
Requires-Dist: ta
Requires-Dist: binance-connector
Requires-Dist: plotly
Requires-Dist: kaleido
Requires-Dist: pandas
